{
   "AdsManager":{
      "adNetwork" :"admob",
      "interstitial_admob":"ca-app-pub-9322101337669156/6266828164",
      "banner_admob":"ca-app-pub-9322101337669156/4924992189",
      "native_admob":"ca-app-pub-9322101337669156/4689188465",

      "interstitial_fan":"IMG_16_9_APP_INSTALL#465986095404427_474869491182754",
      "banner_fan":"IMG_16_9_APP_INSTALL#465986095404427_474834121186291",
      "native_fan":"IMG_16_9_APP_INSTALL#465986095404427_474850511184652"
   },
    "Songs" :[
      {
         "song_name":" Aday ur oufigh",
         "artist":"Aicha Maya",
         "song_link":"https://nadorzik.com/mp3/a/b/f/abf20d38348afcc082e9f789fb8190b7.mp3",
         "image":"https://od.lk/s/NzJfNDMyMzM1MjJf/Aicha%20Maya.png"
      },
      {
         "song_name":"Ad irham rabe",
         "artist":"Aicha Maya",
         "song_link":"https://nadorzik.com/mp3/4/a/8/4a8b57022d65907d24211f6bf375d161.mp3",
         "image":"https://od.lk/s/NzJfNDMyMzM1MjJf/Aicha%20Maya.png"
      },
      {
         "song_name":"Una tret urk ren",
         "artist":"Aicha Maya",
         "song_link":"https://nadorzik.com/mp3/7/e/a/7ea09a78254e03a0ac32d4242ac0e597.mp3",
         "image":"https://od.lk/s/NzJfNDMyMzM1MjJf/Aicha%20Maya.png"
      },
        {
         "song_name":"Awyaten",
         "artist":"Aicha Maya",
         "song_link":"https://nadorzik.com/mp3/9/7/5/97562c3d9fa4fc439fb293165e8017c1.mp3",
         "image":"https://od.lk/s/NzJfNDMyMzM1MjJf/Aicha%20Maya.png"
      },
        {
         "song_name":"Tahidoust",
         "artist":"Aicha Maya",
         "song_link":"https://nadorzik.com/mp3/a/4/a/a4aa291cc3e78594e8e3b9c834c094ea.mp3",
         "image":"https://od.lk/s/NzJfNDMyMzM1MjJf/Aicha%20Maya.png"
      },
        {
         "song_name":"Wayeh Wayeh",
         "artist":"saida-titrit",
         "song_link":"https://nadorzik.com/mp3/6/7/a/67a4f2251faaaef9fd331e67a1af1956.mp3",
         "image":"https://od.lk/s/NzJfNDMyMzM1MjJf/Aicha%20Maya.png"
      },
        {
         "song_name":"Tayri Taroumit",
         "artist":"saida-titrit",
         "song_link":"https://nadorzik.com/mp3/4/7/0/47057156d991ba759fb04dbd00ed163a.mp3",
         "image":"https://od.lk/s/NzJfNDMyMzM1MjJf/Aicha%20Maya.png"
      },
        {
         "song_name":"Tla Lhawa",
         "artist":"fatima-tamanart",
         "song_link":"https://nadorzik.com/mp3/f/fdf94b38450225c740516d96f5f7eb5a.mp3",
         "image":"https://od.lk/s/NzJfNDMyMzM1MjJf/Aicha%20Maya.png"
      },
        {
         "song_name":"Ourad Sbergh Itmara",
         "artist":"fatima-tamanart",
         "song_link":"https://nadorzik.com/mp3/8/8b7de2d0808468de7457383ef0d6f722.mp3",
         "image":"https://od.lk/s/NzJfNDMyMzM1MjJf/Aicha%20Maya.png"
      },
        {
         "song_name":"Lghdert Ayad",
         "artist":"fatima-tamanart",
         "song_link":"https://nadorzik.com/mp3/7/74d25ee9db6b70d4d6a7660b16d6cbe4.mp3",
         "image":"https://od.lk/s/NzJfNDMyMzM1MjJf/Aicha%20Maya.png"
      },
        {
         "song_name":"Lillah-ya-lghadi",
         "artist":"Aicha_Maya",
         "song_link":"https://www.nozika.co//down.php?s_id=49027",
         "image":"https://od.lk/s/NzJfNDMyMzM1MjJf/Aicha%20Maya.png"
      },
        {
         "song_name":"Track1",
         "artist":"Track",
         "song_link":"https://nadorzik.com/mp3/2/c/7/2c7690760b9bf21714437558f9b9529b.mp3",
         "image":"https://od.lk/s/NzJfNDMyMzM1MjJf/Aicha%20Maya.png"
      },
        {
         "song_name":"Track2",
         "artist":"track",
         "song_link":"https://nadorzik.com/mp3/b/e/4/be41cca19a9af9ad6ef2aaae76a4ee7a.mp3",
         "image":"https://od.lk/s/NzJfNDMyMzM1MjJf/Aicha%20Maya.png"
      },
        {
         "song_name":"Track3",
         "artist":"Aicha_Maya",
         "song_link":"https://www.izlanzik.org/uploads/2021/Aicha_Maya/Hawlat.mp3",
         "image":"https://od.lk/s/NzJfNDMyMzM1MjJf/Aicha%20Maya.png"
      },
        {
         "song_name":"track4",
         "artist":"Aicha_Maya",
         "song_link":"https://nadorzik.com/mp3/4/2/e/42e8adafbc105abad862c74f2f1c1251.mp3",
         "image":"https://od.lk/s/NzJfNDMyMzM1MjJf/Aicha%20Maya.png"
      },
        {
         "song_name":"Awissn Matta L3ar As Guig",
         "artist":"Aicha_Maya",
         "song_link":"https://nadorzik.com/mp3/b/d/6/bd6ff3d0c142a0cfe0f2b37fa97fc4c9.mp3",
         "image":"https://od.lk/s/NzJfNDMyMzM1MjJf/Aicha%20Maya.png"
      },
        {
         "song_name":"Nek Our Dmigh",
         "artist":"Track",
         "song_link":"https://nadorzik.com/mp3/f/2/e/f2efa8ad2e95e57a7a3209957ad327fa.mp3",
         "image":"https://od.lk/s/NzJfNDMyMzM1MjJf/Aicha%20Maya.png"
      },
        {
         "song_name":"Ourid Ghas Chy Ayoulinou",
         "artist":"Track",
         "song_link":"https://nadorzik.com/mp3/2/3/9/239b3e6a73440493c8b4e4aaa46f86b1.mp3",
         "image":"https://od.lk/s/NzJfNDMyMzM1MjJf/Aicha%20Maya.png"
      },
        {
         "song_name":"Tedda Tenna Righ",
         "artist":"Track",
         "song_link":"https://nadorzik.com/mp3/b/9/1/b91ddf1722467aaa61772931ebe0e316.mp3",
         "image":"https://od.lk/s/NzJfNDMyMzM1MjJf/Aicha%20Maya.png"
      },
        {
         "song_name":"Tahidoust Iddad Ousmoun Inw",
         "artist":"Aicha_Maya",
         "song_link":"https://nadorzik.com/mp3/0/e/d/0edb51abeac54753b27226a19afef523.mp3",
         "image":"https://od.lk/s/NzJfNDMyMzM1MjJf/Aicha%20Maya.png"
      },
        {
         "song_name":"Ahidouss",
         "artist":"Aicha_Maya",
         "song_link":"https://nadorzik.com/mp3/6/f/b/6fb5164a215aaabc9d817045a395b0d6.mp3",
         "image":"https://od.lk/s/NzJfNDMyMzM1MjJf/Aicha%20Maya.png"
      }
   ]
}
